froid/datasets.py
froid/plotting.py
froid/preprocessing.py
froid/quantification.py
froid/transcription.py
froid/tests/test_datasets.py
froid-0.0.0.dist-info/METADATA
froid-0.0.0.dist-info/WHEEL
froid-0.0.0.dist-info/top_level.txt
froid-0.0.0.dist-info/RECORD
