Metadata-Version: 2.1
Name: froid
Version: 0.0.0
Summary: Dream analysis in Python
Home-page: https://github.com/remrama/froid
Author: Remington Mallett
Author-email: mallett.remy@gmail.com
Project-URL: Homepage, https://github.com/remrama/froid
Project-URL: Source, https://github.com/remrama/froid
Project-URL: Bug Tracker, https://github.com/remrama/froid/issues
Project-URL: Release Notes, https://github.com/remrama/froid/releases
Classifier: Environment :: Console
Classifier: Operating System :: OS Independent
Classifier: License :: OSI Approved :: BSD License
Classifier: Programming Language :: Python :: 3
Classifier: Intended Audience :: Science/Research
Requires-Python: >=3.8
Requires-Dist: matplotlib
Requires-Dist: numpy
Requires-Dist: pandas
Requires-Dist: scipy
